noterools-1.1.4.dist-info/METADATA
noterools-1.1.4.dist-info/WHEEL
noterools/__init__.py
noterools/_entry.py
noterools/bibliography.py
noterools/citation.py
noterools/csl.py
noterools/colors.py
noterools/error.py
noterools/hook.py
noterools/utils.py
noterools/word.py
noterools/zotero.py
noterools-1.1.4.dist-info/RECORD
