Metadata-Version: 2.1
Name: noterools
Version: 1.1.4
Summary: Not just zotero tools.
Keywords: Zotero
Author-Email: Syize <syizeliu@gmail.com>
Maintainer-Email: Syize <syizeliu@gmail.com>
License: GPL-3.0-or-later
Project-URL: homepage, https://github.com/Syize/noterools
Project-URL: repository, https://github.com/Syize/noterools
Project-URL: Bug Tracker, https://github.com/Syize/noterools/issues
Requires-Python: >=3.10
Requires-Dist: pywin32
Requires-Dist: rich
Requires-Dist: pyzotero
Requires-Dist: lxml
